gdrive_fsspec/__init__.py
gdrive_fsspec/_version.py
gdrive_fsspec/core.py
gdrive_fsspec/tests/__init__.py
gdrive_fsspec/tests/test_core.py
gdrive_fsspec-0.4.0.dist-info/licenses/LICENSE
gdrive_fsspec-0.4.0.dist-info/METADATA
gdrive_fsspec-0.4.0.dist-info/WHEEL
gdrive_fsspec-0.4.0.dist-info/top_level.txt
gdrive_fsspec-0.4.0.dist-info/RECORD
