Metadata-Version: 2.4
Name: gdrive_fsspec
Version: 0.4.0
Summary: File system on GDrive
Maintainer-email: Martin Durant <martin.durant@alumni.utoronto.ca>
License: BSD 3-Clause License
Project-URL: Source, http://github.com/fsspec/gdrive-fsspec
Classifier: Development Status :: 4 - Beta
Classifier: Intended Audience :: Developers
Classifier: License :: OSI Approved :: BSD License
Classifier: Operating System :: OS Independent
Classifier: Programming Language :: Python :: 3.10
Classifier: Programming Language :: Python :: 3.11
Classifier: Programming Language :: Python :: 3.12
Classifier: Programming Language :: Python :: 3.13
Classifier: Programming Language :: Python :: 3.14
Requires-Python: >=3.10
License-File: LICENSE
Requires-Dist: fsspec
Requires-Dist: google-api-python-client
Requires-Dist: google-auth-httplib2
Requires-Dist: google-auth-oauthlib
Requires-Dist: pydata_google_auth
Dynamic: license-file
